streamlit_vizzu/__init__.py
streamlit_vizzu/chart.py
streamlit_vizzu/frontend/index.html
streamlit_vizzu/frontend/main.js
streamlit_vizzu/frontend/package-lock.json
streamlit_vizzu/frontend/streamlit-component-lib.js
streamlit_vizzu/frontend/style.css
streamlit_vizzu-0.2.1.dist-info/LICENSE
streamlit_vizzu-0.2.1.dist-info/METADATA
streamlit_vizzu-0.2.1.dist-info/WHEEL
streamlit_vizzu-0.2.1.dist-info/top_level.txt
streamlit_vizzu-0.2.1.dist-info/RECORD
