Metadata-Version: 2.2
Name: streamlit-vizzu
Version: 0.2.1
Summary: Bidirectional streamlit component for interacting with vizzu animations
Author: Zachary Blackwoood
Author-email: zachary@streamlit.io
Requires-Python: >=3.7
License-File: LICENSE
Requires-Dist: streamlit>=1.13.0
Requires-Dist: ipyvizzu>=0.17.0
Dynamic: author
Dynamic: author-email
Dynamic: description
Dynamic: description-content-type
Dynamic: requires-dist
Dynamic: requires-python
Dynamic: summary
